loganalyst/__init__.py
loganalyst/cli.py
loganalyst/models.py
loganalyst/options.py
loganalyst/utils.py
loganalyst-1.0.14.dist-info/METADATA
loganalyst-1.0.14.dist-info/WHEEL
loganalyst-1.0.14.dist-info/entry_points.txt
loganalyst-1.0.14.dist-info/RECORD
